setup.cfg
setup.py
kvpbase/kvpbase.py
kvpbase/test.py
kvpbase/version.py
kvpbase.egg-info/PKG-INFO
kvpbase.egg-info/SOURCES.txt
kvpbase.egg-info/dependency_links.txt
kvpbase.egg-info/top_level.txt