Metadata-Version: 1.0
Name: kvpbase
Version: 1.0.1
Summary: kvpbase Python SDK
Home-page: http://www.kvpbase.com/
Author: ['Joel Christner']
Author-email: joel@maraudersoftware.com
License: MIT
Platform: UNKNOWN
